nada_dsl/__init__.py
nada_dsl/ast_util.py
nada_dsl/compile.py
nada_dsl/compiler_frontend.py
nada_dsl/errors.py
nada_dsl/operations.py
nada_dsl/program_io.py
nada_dsl/source_ref.py
nada_dsl/timer.py
nada_dsl/audit/__init__.py
nada_dsl/audit/__main__.py
nada_dsl/audit/abstract.py
nada_dsl/audit/common.py
nada_dsl/audit/report.py
nada_dsl/audit/strict.py
nada_dsl/future/__init__.py
nada_dsl/future/operations.py
nada_dsl/nada_types/__init__.py
nada_dsl/nada_types/collections.py
nada_dsl/nada_types/function.py
nada_dsl/nada_types/generics.py
nada_dsl/nada_types/scalar_types.py
nada_dsl-0.8.0.dist-info/LICENSE
nada_dsl-0.8.0.dist-info/METADATA
nada_dsl-0.8.0.dist-info/WHEEL
nada_dsl-0.8.0.dist-info/top_level.txt
nada_dsl-0.8.0.dist-info/RECORD
