Metadata-Version: 2.2
Name: nada_dsl
Version: 0.8.0
Summary: Nillion Nada DSL to create Nillion MPC programs.
License:                                  Apache License
Classifier: License :: OSI Approved :: Apache Software License
Requires-Python: >=3.10
License-File: LICENSE
Requires-Dist: asttokens~=2.4
Requires-Dist: richreports~=0.2
Requires-Dist: parsial~=0.1
Requires-Dist: sortedcontainers~=2.4
Requires-Dist: typing_extensions~=4.12.2
Requires-Dist: nada-mir-proto==0.2.0
Requires-Dist: types-protobuf~=5.29
Provides-Extra: docs
Requires-Dist: toml~=0.10.2; extra == "docs"
Requires-Dist: sphinx<9,>=5; extra == "docs"
Requires-Dist: sphinx-rtd-theme<3.1,>=1.0; extra == "docs"
Requires-Dist: sphinx-autoapi~=3.3.2; extra == "docs"
Provides-Extra: test
Requires-Dist: pytest<9.0,>=7.4; extra == "test"
Requires-Dist: pytest-cov<7,>=4; extra == "test"
Provides-Extra: lint
Requires-Dist: pylint<3.4,>=2.17; extra == "lint"
